[ { "name": "bezier", "template": { "type": "greensock", "div": "Titelei", "time": 500, "desc": "Bezier", "duration": 1700, "fontSize": "7em", "bezier": [ { "left": 100, "top": 250 }, { "left": 300, "top": 0 }, { "left": 500, "top": 400 } ], "done": true }, "_id": "0d7QHul4pYNCJRyt" }, { "name": "bezier_rotation", "template": { "type": "greensock", "div": "Titelei", "time": 500, "desc": "Bezier Rotation", "duration": 1700, "bezier": { "curviness": 1.25, "values": [ { "x": 100, "y": 250 }, { "x": 300, "y": 0 }, { "x": 500, "y": 400 } ], "autoRotate": true }, "done": true }, "_id": "9EtWBRaK3PHeLdip" }, { "name": "change_text", "template": { "type": "change_text", "div": "Sample", "text": "This is a new text", "time": 3464, "duration": 20, "done": true }, "_id": "hfgvDX9C1CNIQgFj" }, { "name": "fx_explosion", "template": { "type": "splittext", "subtype": "explosion", "splitting": "letters", "div": "Fenster", "time": 5500, "duration": 400, "desc": "Explosion", "css": { "color": "white", "scale": 3, "ease": "Elastic.easeOut" }, "done": false }, "_id": "5SO8iCzvqAdL7cik" }, { "name": "fx_machinegun", "template": { "type": "splittext", "subtype": "machine_gun", "div": "Fenster", "time": 5500, "duration": 7700, "rhythm": 1300, "desc": "Hintergrund wird rot", "css": { "color": "white", "scale": 3, "ease": "Elastic.easeOut" }, "done": false }, "_id": "IOCOzKhuWhlWYSPK" }, { "name": "fx_machinegun_shadow", "template": { "type": "splittext", "subtype": "machine_gun", "div": "Fenster", "time": 5500, "duration": 7700, "rhythm": 1300, "desc": "Hintergrund wird rot", "css": { "color": "yellow", "textShadow": "0 0 30px black", "scale": 3, "ease": "Elastic.easeOut" }, "done": false }, "_id": "zVBkWfJiBJJwRrmj" }, { "name": "fx_randomcolors", "template": { "type": "splittext", "subtype": "random_colors", "splitting": "letters", "div": "Fenster", "time": 5500, "duration": 2400, "desc": "Explosion", "css": { "color": "white", "scale": 3, "ease": "Elastic.easeOut" }, "done": false }, "_id": "713AiKgMjiHl5e8E" }, { "name": "fx_typewriter", "template": { "type": "typewriter", "time": 2480, "text": "typing this txt is easy", "div": "Fenster", "color": "rgb(0, 80,200)", "duration": 2000, "fontSize": "30px", "done": true }, "_id": "MvtSSNGqyU9sLVMO" }, { "name": "raphael_new_paper", "template": { "type": "raphael", "subtype": "create_paper", "div": "Titelei", "time": 4200, "duration": 20, "desc": "Raphael new paper", "width": 300, "height": 300, "attr": { "fill": "rgb(255,0,0)", "stroke": "black", "opacity": 0.98 }, "done": false }, "_id": "BfjiYtXXWCpF4uqO" }, { "name": "raphael_remove_element", "template": { "type": "raphael", "subtype": "remove", "id": "Hans", "time": 8129, "duration": 20, "desc": "Raphael remove element", "width": 300, "height": 300, "attr": { "fill": "rgb(255,0,0)", "stroke": "black", "opacity": 0.98 }, "done": false }, "_id": "Pb5uxXy74I0sEewY" }, { "name": "raphael_sequence", "template": { "type": "raphael_sequence", "div": "Titelei", "time": 4700, "desc": "sequence", "events": [ { "type": "create_paper", "width": 100, "height": 100 }, { "type": "circle", "cx": 0, "cy": 0, "r": 50, "attr": { "fill": "blue" } }, { "type": "animate", "duration": 400, "attr": { "cx": 50, "cy": 50, "r": 20, "fill": "yellow" } } ], "done": false }, "_id": "nu7xLy5IWz95AdlL" }, { "name": "simple", "template": { "type": "greensock", "div": "Fenster", "time": 107, "desc": "Hintergrund wird rot", "color": "red", "duration": 1700, "fontSize": "7em", "left": 100, "ease": "Sine.easeOut", "done": true }, "_id": "Ql7ISXQXYrHAE7R4" }, { "name": "simple_fontsize", "template": { "type": "greensock", "div": "Sample", "time": 3836, "desc": "fontsize", "duration": 0, "fontSize": "5em", "done": false }, "_id": "HmE3LOfBfQeHrrGN" }, { "name": "simple_pos", "template": { "type": "greensock", "div": "Sample", "time": 4643, "desc": "Hintergrund wird rot", "duration": 0, "left": 0, "top": 0, "width": "100%", "height": "100%", "done": false }, "_id": "PKoAyTGhS0gDWSyD" }, { "name": "split_grotesque", "template": { "type": "splittext", "subtype": "shivering", "splitting": "letters", "div": "Fenster", "time": 5500, "duration": 2400, "desc": "Explosion", "css": { "color": "white", "scale": 3, "ease": "Elastic.easeOut" }, "done": false }, "_id": "9gLB1KQzhyULUha5" }, { "name": "split_machinegun", "template": { "type": "splittext", "subtype": "machine_gun", "div": "Fenster", "time": 5500, "duration": 7700, "rhythm": 300, "desc": "Hintergrund wird rot", "css": { "color": "white", "scale": 3, "ease": "Elastic.easeOut" }, "done": false }, "_id": "71q1CqA7XGfsp9iw" }, { "name": "split_scrambled", "template": { "type": "splittext", "subtype": "shivering", "splitting": "letters", "div": "Fenster", "time": 5500, "duration": 2400, "desc": "Explosion", "css": { "color": "white", "scale": 3, "ease": "Elastic.easeOut" }, "done": false }, "_id": "tzwQ5Db8kAJl9Cco" }, { "name": "text-shadow-3d-effect", "template": { "type": "greensock", "div": "Titelei", "time": 2647, "desc": "3d effect", "duration": 40, "color": "white", "textShadow": "0px 1px 0px #999, 0px 2px 0px #888, 0px 3px 0px #777, 0px 4px 0px #666, 0px 5px 0px #555, 0px 6px 0px #444, 0px 7px 0px #333, 0px 8px 7px #001135", "ease": "Sine.easeOut", "done": true }, "_id": "6ILRUKVLbFIOHiOV" }, { "name": "text-shadow-blurred", "template": { "type": "greensock", "div": "Titelei", "time": 500, "desc": "blurred-text", "duration": 500, "color": "transparent", "textShadow": "0 0 15px #000;", "ease": "Sine.easeOut", "done": true }, "_id": "gVy1wS2TYtCfr5ZR" }, { "name": "text-shadow-burning", "template": { "type": "greensock", "div": "Titelei", "time": 2647, "desc": "bruning", "duration": 20, "color": "white", "textShadow": "0px -1px 4px white, 0px -2px 10px yellow, 0px -10px 20px #ff8000, 0px -18px 40px red", "ease": "Sine.easeOut", "done": true }, "_id": "XxI00GA5t1G9kmTx" }, { "name": "text-shadow-cream", "template": { "type": "greensock", "div": "Fenster", "time": 2500, "desc": "cream", "duration": 500, "color": "hsl(35, 100%, 30%)", "textShadow": "0 0 4px 2px hsl(35, 70%, 30%), 0 0 6px 6px hsla(30, 100%, 55%, 0.5)", "done": true }, "_id": "9FQit5R7yeqgHzjo" }, { "name": "text-shadow-elegant", "template": { "type": "greensock", "div": "Fenster", "time": 2500, "desc": "elegant shadow", "color": "white", "duration": 1700, "textShadow": "1px -1px 0 #767676, -1px 2px 1px #737272, -2px 4px 1px #767474, -3px 6px 1px #787777, -4px 8px 1px #7b7a7a, -5px 10px 1px #7f7d7d, -6px 12px 1px #828181, -7px 14px 1px #868585, -8px 16px 1px #8b8a89, -9px 18px 1px #8f8e8d, -10px 20px 1px #949392, -11px 22px 1px #999897, -12px 24px 1px #9e9c9c, -13px 26px 1px #a3a1a1, -14px 28px 1px #a8a6a6, -15px 30px 1px #adabab, -16px 32px 1px #b2b1b0, -17px 34px 1px #b7b6b5, -18px 36px 1px #bcbbba, -19px 38px 1px #c1bfbf, -20px 40px 1px #c6c4c4, -21px 42px 1px #cbc9c8, -22px 44px 1px #cfcdcd, -23px 46px 1px #d4d2d1, -24px 48px 1px #d8d6d5, -25px 50px 1px #dbdad9, -26px 52px 1px #dfdddc, -27px 54px 1px #e2e0df, -28px 56px 1px #e4e3e2", "done": true }, "_id": "DddcH4cCQnOvcsAC" }, { "name": "text-shadow-embossed", "template": { "type": "greensock", "div": "Titelei", "time": 2647, "desc": "embossed", "duration": 20, "color": "gray", "textShadow": "-1px -1px 1px #fff, 1px 1px 1px #000", "ease": "Sine.easeOut", "done": true }, "_id": "HLYRRJzb0qG2OYyh" }, { "name": "text-shadow-lens-flare", "template": { "type": "greensock", "div": "Titelei", "time": 2647, "desc": "lense flare", "duration": 40, "color": "white", "textShadow": "0 0 150px #FFF, 0 0 60px #FFF, 0 0 10px #FFF", "ease": "Sine.easeOut", "done": true }, "_id": "PRhyjullC8g96uIA" }, { "name": "text-shadow-letterpress", "template": { "type": "greensock", "div": "Titelei", "time": 500, "desc": "letterpress", "duration": 0, "color": "gray", "textShadow": "0 -1px 1px #666666, 0 1px 1px #FFFFFF", "ease": "Sine.easeOut", "done": true }, "_id": "K4OrV7M3ZhDFf1mx" }, { "name": "text-shadow-neon", "template": { "type": "greensock", "div": "Titelei", "time": 500, "desc": "neon", "duration": 1000, "color": "black", "textShadow": "0 0 10px #FFFFFF, 0 0 20px #FFFFFF, 0 0 30px #FFFFFF, 0 0 40px #FF00DE, 0 0 70px #FF00DE,0 0 80px #FF00DE, 0 0 100px #FF00DE, 0 0 150px #FF00DE", "ease": "Sine.easeOut", "done": true }, "_id": "mWJredDUj9zugAld" }, { "name": "text-shadow-neon-blue", "template": { "type": "greensock", "div": "Fenster", "time": 2500, "desc": "pruple glow", "duration": 1000, "color": "white", "textShadow": "0 0 5px #fff, 0 0 10px #fff, 0 0 15px #fff, 0 0 20px #228DFF, 0 0 35px #228DFF, 0 0 40px #228DFF, 0 0 50px #228DFF, 0 0 75px #228DFF", "ease": "Sine.easeOut", "done": true }, "_id": "frU10Ae4UL1A0V0l" }, { "name": "text-shadow-neon-green", "template": { "type": "greensock", "div": "Titelei", "time": 469, "desc": "neon green", "duration": 1000, "color": "white", "textShadow": "0 0 3px #fff, 0 0 7px #fff, 0 0 11px #fff, 0 0 17px #2dff2d, 0 0 27px #2dff2d, 0 0 37px #2dff2d, 0 0 47px #2dff2d, 0 0 77px #2dff2d", "ease": "Sine.easeOut", "done": true }, "_id": "I8AfzbL533tk9rAB" }, { "name": "text-shadow-neon-yellow", "template": { "type": "greensock", "div": "Titelei", "time": 469, "desc": "pruple glow", "duration": 1000, "color": "white", "textShadow": "0 0 5px #fff, 0 0 10px #fff, 0 0 15px #fff, 0 0 20px #FFDD1B, 0 0 35px #FFDD1B, 0 0 40px #FFDD1B, 0 0 50px #FFDD1B, 0 0 75px #FFDD1B", "ease": "Sine.easeOut", "done": true }, "_id": "Twn57ligY99YSSRc" }, { "name": "text-shadow-pink-neon", "template": { "type": "greensock", "div": "Titelei", "time": 2647, "desc": "pink neon", "duration": 20, "color": "white", "textShadow": "0 0 5px #fff, 0 0 10px #fff, 0 0 15px #fff, 0 0 20px #ff2d95, 0 0 30px #ff2d95, 0 0 40px #ff2d95, 0 0 50px #ff2d95, 0 0 75px #ff2d95", "ease": "Sine.easeOut", "done": true }, "_id": "naKUiJx4hW3kzufG" }, { "name": "text-shadow-pink-neon2", "template": { "type": "greensock", "div": "Titelei", "time": 500, "desc": "pink neon 2", "color": "white", "duration": 1700, "textShadow": "0 0 10px #fff, 0 0 20px #fff, 0 0 30px #fff, 0 0 40px #ff00de, 0 0 70px #ff00de, 0 0 80px #ff00de, 0 0 100px #ff00de, 0 0 150px #ff00de", "done": true }, "_id": "wkb4eP95LCBobL3u" }, { "name": "text-shadow-purple-glow", "template": { "type": "greensock", "div": "Titelei", "time": 500, "desc": "pruple glow", "duration": 1000, "color": "white", "textShadow": "0 0 0.2em #8877FF, 0 0 0.2em #8877FF, 0 0 0.2em black", "ease": "Sine.easeOut", "done": true }, "_id": "UiUwDSrYx4tHXhQr" }, { "name": "text-shadow-reset", "template": { "type": "greensock", "div": "Titelei", "time": 8101, "desc": "glow", "duration": 1700, "textShadow": "none", "ease": "Sine.easeOut", "done": true }, "_id": "Jge5nOahktteywTc" }, { "name": "text-shadow-retro", "template": { "type": "greensock", "div": "Titelei", "time": 2647, "desc": "retro", "duration": 30, "color": "#d7ceb2", "textShadow": "3px 3px 0px #2c2e38, 5px 5px 0px #5c5f72", "ease": "Sine.easeOut", "done": true }, "_id": "QeKZPqCj0ENBnERz" }, { "name": "text-shadow-simple", "template": { "type": "greensock", "div": "Titelei", "time": 500, "desc": "glow", "duration": 1700, "textShadow": "5px 5px 5px #000", "ease": "Sine.easeOut", "done": true }, "_id": "4XDs32XiZX8Z67SG" }, { "name": "text-small-caps", "template": { "type": "greensock", "div": "Fenster", "time": 500, "desc": "small caps", "color": "white", "duration": 1700, "textTransform": "uppercase", "textShadow": "#363535 3px 3px 5px", "fontVariant": "small-caps", "done": true }, "_id": "d9wuXHnEoXIXZRA0" }, { "name": "text-stroke", "template": { "type": "greensock", "div": "Titelei", "time": 2647, "desc": "text stroke", "duration": 40, "color": "transparent", "webkitTextStroke": "white", "ease": "Sine.easeOut", "done": true }, "_id": "jB6PQPaAny0hVj90" }, { "name": "text-stroke-white", "template": { "type": "greensock", "div": "Titelei", "time": 500, "desc": "text stroke", "duration": 40, "webkitTextFillColor": "transparent", "webkitTextStroke": "2px white", "ease": "Sine.easeOut", "done": true }, "_id": "SwTXhthc5PQElwrA" }, { "name": "text_contnuous_right_to_left", "template": { "type": "greensockArray", "div": "Titelei", "time": 522, "duration": 11000, "events": [ { "duration": 0, "left": "120%", "ease": "Bounce.easeIn" }, { "duration": 11000, "left": "-120%", "delay": 500, "ease": "Sine.easeInOut" } ], "done": true }, "_id": "UMHF5lPwmuzKhGpU" }, { "name": "text_down", "template": { "type": "greensockArray", "div": "Titelei", "time": 4500, "duration": 1500, "events": [ { "duration": 0, "top": -1000, "color": "blue", "letterSpacing": "-2", "ease": "Bounce.easeIn" }, { "duration": 3500, "top": 1000, "color": "orange", "delay": 500 } ], "done": false }, "_id": "j3WVj9rUheq6L23n" }, { "name": "text_left_to_right", "template": { "type": "greensockArray", "div": "Titelei", "time": 533, "duration": 500, "events": [ { "duration": 0, "left": "-100%", "color": "blue", "letterSpacing": "-2", "ease": "Bounce.easeIn" }, { "duration": 3500, "left": 100, "color": "orange", "delay": 500 }, { "left": "100%", "duration": 4000 } ], "done": false }, "_id": "TXkX7MWYsAY6vYSa" }, { "name": "text_left_to_right_with_stop", "template": { "type": "greensockArray", "div": "Fenster", "time": 2500, "duration": 3500, "events": [ { "duration": 0, "left": "-100%", "color": "blue", "letterSpacing": "-2", "ease": "Bounce.easeIn" }, { "duration": 3500, "left": 100, "color": "orange", "delay": 500 }, { "left": "100%", "delay": 4000 } ], "done": false }, "_id": "Dz9SIB6DUoCkMazK" }, { "name": "text_replacement", "template": { "type": "greensock", "div": "Titelei", "time": 3072, "desc": "TEXT CHANGE", "duration": 500, "text": "NEW TEXT", "done": true }, "_id": "nthNar3LHDrrpbDG" }, { "name": "text_stop_right_left_elastic", "template": { "type": "greensockArray", "div": "Titelei", "time": 522, "duration": 3500, "events": [ { "duration": 0, "left": "102%", "ease": "Bounce.easeIn" }, { "duration": 3000, "left": "18%", "delay": 500, "ease": "Elastic.easeOut" }, { "left": "-120%", "delay": 6000, "duration": 3000, "ease": "Sine.easeIn" } ], "done": true }, "_id": "cFqFDhV8zZmh57kl" }, { "name": "text_stop_right_to_left", "template": { "type": "greensockArray", "div": "Titelei", "time": 522, "duration": 3500, "events": [ { "duration": 0, "left": "120%", "ease": "Bounce.easeIn" }, { "duration": 4000, "left": "8%", "delay": 500, "ease": "Sine.easeOut" }, { "left": "-120%", "delay": 6000, "duration": 3000 } ], "done": false }, "_id": "cNkdgLlWFb2JHK2b" }, { "name": "text_stop_right_to_left_elastic_scaling", "template": { "type": "greensockArray", "div": "Fenster", "time": 107, "duration": 3500, "events": [ { "duration": 0, "left": "102%", "ease": "Bounce.easeIn" }, { "duration": 3000, "left": "18%", "delay": 500, "scale": 1.5, "ease": "Elastic.easeOut" }, { "left": "-120%", "scale": 1, "duration": 3000, "delay": 3500, "ease": "Sine.easeIn" } ], "done": true }, "_id": "K5CuTDrc0FIdRTEm" }, { "name": "text_up", "template": { "type": "greensockArray", "div": "Fenster", "time": 6802, "duration": 3500, "events": [ { "duration": 0, "top": 1000, "color": "blue", "letterSpacing": "-2", "ease": "Bounce.easeIn" }, { "duration": 3500, "top": -1000, "color": "orange", "delay": 500 } ], "done": false }, "_id": "R7cGwzkjjrDE6S5Q" } ]